config/__init__.py
mtrl/__init__.py
mtrl/logger.py
mtrl/replay_buffer.py
mtrl/agent/__init__.py
mtrl/agent/abstract.py
mtrl/agent/deepmdp.py
mtrl/agent/distral.py
mtrl/agent/grad_manipulation.py
mtrl/agent/gradnorm.py
mtrl/agent/hipbmdp.py
mtrl/agent/pcgrad.py
mtrl/agent/sac.py
mtrl/agent/sac_ae.py
mtrl/agent/utils.py
mtrl/agent/wrapper.py
mtrl/agent/components/__init__.py
mtrl/agent/components/actor.py
mtrl/agent/components/base.py
mtrl/agent/components/critic.py
mtrl/agent/components/decoder.py
mtrl/agent/components/encoder.py
mtrl/agent/components/hipbmdp_theta.py
mtrl/agent/components/moe_layer.py
mtrl/agent/components/reward_decoder.py
mtrl/agent/components/soft_modularization.py
mtrl/agent/components/task_encoder.py
mtrl/agent/components/transition_model.py
mtrl/agent/ds/__init__.py
mtrl/agent/ds/mt_obs.py
mtrl/agent/ds/task_info.py
mtrl/app/__init__.py
mtrl/app/run.py
mtrl/env/__init__.py
mtrl/env/builder.py
mtrl/env/types.py
mtrl/env/vec_env.py
mtrl/experiment/__init__.py
mtrl/experiment/dmcontrol.py
mtrl/experiment/experiment.py
mtrl/experiment/metaworld.py
mtrl/experiment/multitask.py
mtrl/experiment/utils.py
mtrl/utils/__init__.py
mtrl/utils/checkpointable.py
mtrl/utils/config.py
mtrl/utils/types.py
mtrl/utils/utils.py
mtrl/utils/video.py
mtrl-1.0.0.dist-info/LICENSE
mtrl-1.0.0.dist-info/METADATA
mtrl-1.0.0.dist-info/WHEEL
mtrl-1.0.0.dist-info/top_level.txt
mtrl-1.0.0.dist-info/RECORD
