Metadata-Version: 2.1
Name: mtrl
Version: 1.0.0
Summary: MTRL: Multi Task RL Algorithms
Home-page: https://github.com/facbookresearch/mtrl
Author: Shagun Sodhani, Amy Zhang
Author-email: sshagunsodhani@gmail.com, amyzhang@fb.com
License: UNKNOWN
Platform: UNKNOWN
Classifier: Programming Language :: Python :: 3.6
Classifier: Programming Language :: Python :: 3.7
Classifier: Programming Language :: Python :: 3.8
Classifier: Programming Language :: Python :: 3.9
Classifier: License :: OSI Approved :: MIT License
Classifier: Operating System :: POSIX :: Linux
Requires-Python: >=3.6
Requires-Dist: imageio-ffmpeg (==0.4.3)
Requires-Dist: hydra-core (==1.0.5)
Requires-Dist: hydra-submitit-launcher (==1.0.1)
Requires-Dist: imageio (==2.9.0)
Requires-Dist: mllogger (==0.7)
Requires-Dist: numpy (==1.19.5)
Requires-Dist: opencv-python (==4.5.1.48)
Requires-Dist: pillow (==7.1.0)
Requires-Dist: termcolor (==1.1.0)
